vim_plugin_metadata-0.2.2.dist-info/METADATA
vim_plugin_metadata-0.2.2.dist-info/WHEEL
vim_plugin_metadata.libs/libgcc_s-b5472b99.so.1
vim_plugin_metadata/__init__.py
vim_plugin_metadata/__init__.pyi
vim_plugin_metadata/py.typed
vim_plugin_metadata/vim_plugin_metadata.abi3.so
vim_plugin_metadata-0.2.2.dist-info/RECORD
