Metadata-Version: 2.3
Name: vim-plugin-metadata
Version: 0.2.2
Classifier: Development Status :: 2 - Pre-Alpha
Classifier: Intended Audience :: Developers
Classifier: Programming Language :: Rust
Classifier: Programming Language :: Python :: Implementation :: CPython
Classifier: Programming Language :: Python :: Implementation :: PyPy
Classifier: Topic :: Software Development :: Libraries
Summary: Parse and analyze your vim plugins
Keywords: vim,parsing,tree-sitter
Author: David Barnett
License: MIT
Requires-Python: >=3.8
Project-URL: Repository, https://github.com/dbarnett/rust-vim-plugin-metadata
Project-URL: Issues, https://github.com/dbarnett/rust-vim-plugin-metadata/issues
